quickci/__init__.py
quickci/classes.py
quickci/cli.py
quickci/quickci.py
quickci/commands/__init__.py
quickci/commands/config.py
quickci/commands/status.py
quickci-0.4.0.dist-info/AUTHORS.rst
quickci-0.4.0.dist-info/LICENSE
quickci-0.4.0.dist-info/METADATA
quickci-0.4.0.dist-info/WHEEL
quickci-0.4.0.dist-info/entry_points.txt
quickci-0.4.0.dist-info/top_level.txt
quickci-0.4.0.dist-info/RECORD
