Metadata-Version: 2.1
Name: quickci
Version: 0.4.0
Summary: Have a quick look at the status of CI projects from the command line.
Home-page: https://github.com/robertopreste/quickci
Author: Roberto Preste
Author-email: robertopreste@gmail.com
License: MIT license
Keywords: quickci
Platform: UNKNOWN
Classifier: Development Status :: 2 - Pre-Alpha
Classifier: Intended Audience :: Developers
Classifier: License :: OSI Approved :: MIT License
Classifier: Natural Language :: English
Classifier: Programming Language :: Python :: 3
Classifier: Programming Language :: Python :: 3.5
Classifier: Programming Language :: Python :: 3.6
Classifier: Programming Language :: Python :: 3.7
Requires-Dist: Click (>=7.0)
Requires-Dist: requests (>=2.21.0)
Requires-Dist: asyncio (>=3.4.3)
Requires-Dist: aiohttp (>=3.5.4)
